idd_iterator/__init__.py
idd_iterator/__main__.py
idd_iterator/idd_multimodal_iterator.py
IDD_Iterator-1.0.2.dist-info/METADATA
IDD_Iterator-1.0.2.dist-info/WHEEL
IDD_Iterator-1.0.2.dist-info/top_level.txt
IDD_Iterator-1.0.2.dist-info/RECORD
