Metadata-Version: 2.1
Name: IDD-Iterator
Version: 1.0.2
Summary: IDD Iterator
Home-page: UNKNOWN
License: UNKNOWN
Platform: OS Independent
Requires-Dist: pandas
